fake_html/__init__.py
fake_html/config/__init__.py
fake_html/config/meta.py
fake_html/crawl/__init__.py
fake_html/crawl/__main__.py
fake_html/dataset/__init__.py
fake_html/dataset/baidu_home.html
fake_html/dataset/baidu_search.html
fake_html/dataset/car_home.html
fake_html/dataset/csdn_article_1.html
fake_html/dataset/csdn_article_2.html
fake_html/dataset/github_repo_1.html
fake_html/dataset/github_repo_2.html
fake_html/dataset/github_source_1.html
fake_html/dataset/github_source_2.html
fake_html/dataset/huggingface_card.html
fake_html/dataset/huggingface_files_1.html
fake_html/dataset/huggingface_files_2.html
fake_html/dataset/zhihu_article_1.html
fake_html/dataset/zhihu_article_2.html
fake_html/dataset/zhihu_question_1.html
fake_html/dataset/zhihu_question_2.html
fake_html/markov/__init__.py
fake_html/markov/base.py
fake_html/markov/construct.py
fake_html/markov/dispatch.py
fake_html/markov/model.py
fake_html/utils/__init__.py
fake_html/utils/cli.py
fake_html/utils/requests.py
fake_html/utils/selenium.py
fake_html/utils/sequence.py
fake_html/utils/string.py
fake_html-0.0.2.dist-info/LICENSE
fake_html-0.0.2.dist-info/METADATA
fake_html-0.0.2.dist-info/WHEEL
fake_html-0.0.2.dist-info/top_level.txt
fake_html-0.0.2.dist-info/RECORD
